pyprof/__init__.py
pyprof/prof_proxy.py
pyprof/py.typed
pyprof/pyprof.py
pyprof-1.0.0.dist-info/LICENSE
pyprof-1.0.0.dist-info/METADATA
pyprof-1.0.0.dist-info/WHEEL
pyprof-1.0.0.dist-info/RECORD
