Metadata-Version: 2.1
Name: pyprof
Version: 1.0.0
Summary: This package focus on build time profiler for python functions and snippets.
License: MIT
Author: Zeyan Li 李则言
Author-email: lizeyan.42@bytedance.com
Requires-Python: >=3.9
Classifier: License :: OSI Approved :: MIT License
Classifier: Programming Language :: Python :: 3
Classifier: Programming Language :: Python :: 3.9
Classifier: Programming Language :: Python :: 3.10
Classifier: Programming Language :: Python :: 3.11
Classifier: Programming Language :: Python :: 3.12
